CHANGES.txt
MANIFEST.in
README.md
setup.py
js/__init__.py
js.bootstrap_slider.egg-info/PKG-INFO
js.bootstrap_slider.egg-info/SOURCES.txt
js.bootstrap_slider.egg-info/dependency_links.txt
js.bootstrap_slider.egg-info/entry_points.txt
js.bootstrap_slider.egg-info/namespace_packages.txt
js.bootstrap_slider.egg-info/not-zip-safe
js.bootstrap_slider.egg-info/requires.txt
js.bootstrap_slider.egg-info/top_level.txt
js/bootstrap_slider/__init__.py
js/bootstrap_slider/test_bootstrap-slider.txt
js/bootstrap_slider/resources/bootstrap-slider.css
js/bootstrap_slider/resources/bootstrap-slider.js
js/bootstrap_slider/resources/bootstrap-slider.min.css
js/bootstrap_slider/resources/bootstrap-slider.min.js