Metadata-Version: 1.0
Name: js.bootstrap-slider
Version: 3.1.0-1
Summary: Fanstatic packaging of bootstrap-slider
Home-page: UNKNOWN
Author: Fanstatic Developers
Author-email: fanstatic@googlegroups.com
License: BSD
Platform: UNKNOWN
